<list display="StringFuncs">
  <action id="osmedile.intellij.stringmanip.UnescapeJavascriptAction" />
  <action id="osmedile.intellij.stringmanip.EscapeHtmlAction" />
  <action id="osmedile.intellij.stringmanip.EscapeJavaAction" />
  <action id="osmedile.intellij.stringmanip.EscapePHPAction" />
  <action id="osmedile.intellij.stringmanip.UnescapePHPAction" />
  <action id="osmedile.intellij.stringmanip.EscapeSQLAction" />
  <action id="osmedile.intellij.stringmanip.UnicodeEscapedToStringAction" />
  <action id="osmedile.intellij.stringmanip.NonAsciiToUnicodeEscapedAction" />
  <action id="osmedile.intellij.stringmanip.UnescapeJavaAction" />
  <action id="osmedile.intellij.stringmanip.UnescapeHtmlAction" />
  <action id="osmedile.intellij.stringmanip.EscapeJavaScriptAction" />
  <action id="QuickList.$Separator$" />
  <action id="osmedile.intellij.stringmanip.EncodeBase64Action" />
  <action id="osmedile.intellij.stringmanip.EncodeMd5Hex16Action" />
  <action id="osmedile.intellij.stringmanip.DecodeBase64Action" />
  <action id="osmedile.intellij.stringmanip.URLEncodeAction" />
  <action id="osmedile.intellij.stringmanip.URLDecodeAction" />
  <action id="QuickList.$Separator$" />
  <action id="osmedile.intellij.stringmanip.PopupChoiceAction" />
  <action id="QuickList.$Separator$" />
  <action id="StringManipulation.ToPascalCaseOrCamelCase" />
  <action id="osmedile.intellij.stringmanip.RemoveAllSpacesAction" />
  <action id="osmedile.intellij.stringmanip.WordsCapitalizeAction" />
  <action id="osmedile.intellij.stringmanip.WordsAndCamelToConstantStyleCaseAction" />
  <action id="StringManipulation.ToHyphenCaseOrCamelCase" />
  <action id="StringManipulation.ToHyphenCaseAction" />
  <action id="StringManipulation.AlignToColumns" />
  <action id="osmedile.intellij.stringmanip.GrepAction" />
  <action id="ShowRegistry" />
  <action id="StringManipulation.ToDotStyleAction" />
  <action id="osmedile.intellij.stringmanip.ToCamelCaseAction" />
  <action id="StringManipulation.RemoveDuplicateLines" />
  <action id="StringManipulation.SwitchStyleAction" />
  <action id="osmedile.intellij.stringmanip.WordsCapitalizeFullyAction" />
  <action id="StringManipulation.ToSnakeCaseOrCamelCase" />
  <action id="osmedile.intellij.stringmanip.SwapCharactersAction" />
  <action id="osmedile.intellij.stringmanip.RemoveEmptyLinesAction" />
  <action id="osmedile.intellij.stringmanip.TrimAllSpacesAction" />
  <action id="osmedile.intellij.stringmanip.TrimAction" />
  <action id="SurroundWith" />
  <action id="Generate" />
  <action id="StructuralSearchPlugin.StructuralSearchAction" />
  <action id="FillParagraph" />
</list>